Metadata-Version: 1.0
Name: jdl
Version: 0.1
Summary: json data logger
Home-page: https://github.com/hash-p-3/json-data-logger
Author: UNKNOWN
Author-email: UNKNOWN
License: UNKNOWN
Platform: UNKNOWN
